Workbook
Name SelScenario: Controls!$C$4

Sheet README

Sheet Transactions_Cashflows
A1: Period | B1: Operating_Inflows | C1: Operating_Outflows | D1: Investing_Outflows | E1: Financing_Inflows | F1: Financing_Outflows | G1: Net_Cash_Flow | H1: Opening_Cash | I1: Closing_Cash | J1: Net_cash_Flow2 | K1: Free_Cash_Flow | L1: Cash_Buffer_Months
A2: 45292 | B2: 939.7 | C2: 711.9 | D2: 267.2 | E2: 98.9 | F2: 127.4 | G2: -67.9 | H2: 3500 | I2: 3432.1 | J2: =TblCash[[#This Row],[Operating_Inflows]]-TblCash[[#This Row],[Operating_Outflows]]-TblCash[[#This Row],[Investing_Outflows]]+TblCash[[#This Row],[Financing_Inflows]]-TblCash[[#This Row],[Financing_Outflows]] -> -67.9 | K2: =TblCash[[#This Row],[Operating_Inflows]]-TblCash[[#This Row],[Operating_Outflows]]-TblCash[[#This Row],[Investing_Outflows]] -> -39.4 | L2: =TblCash[[#This Row],[Closing_Cash]]/TblCash[[#This Row],[Operating_Outflows]]+TblCash[[#This Row],[Financing_Outflows]] -> 132.22104
A3: 45323 | B3: 888.9 | C3: 757.8 | D3: 161.8 | E3: 146.9 | F3: 126.5 | G3: -10.3 | H3: 3432.1 | I3: 3421.8 | J3: =TblCash[[#This Row],[Operating_Inflows]]-TblCash[[#This Row],[Operating_Outflows]]-TblCash[[#This Row],[Investing_Outflows]]+TblCash[[#This Row],[Financing_Inflows]]-TblCash[[#This Row],[Financing_Outflows]] -> -10.3 | K3: =TblCash[[#This Row],[Operating_Inflows]]-TblCash[[#This Row],[Operating_Outflows]]-TblCash[[#This Row],[Investing_Outflows]] -> -30.7 | L3: =TblCash[[#This Row],[Closing_Cash]]/TblCash[[#This Row],[Operating_Outflows]]+TblCash[[#This Row],[Financing_Outflows]] -> 131.01544
A4: 45352 | B4: 951.8 | C4: 669.4 | D4: 266.2 | E4: 21.4 | F4: 120.1 | G4: -82.5 | H4: 3421.8 | I4: 3339.3 | J4: =TblCash[[#This Row],[Operating_Inflows]]-TblCash[[#This Row],[Operating_Outflows]]-TblCash[[#This Row],[Investing_Outflows]]+TblCash[[#This Row],[Financing_Inflows]]-TblCash[[#This Row],[Financing_Outflows]] -> -82.5 | K4: =TblCash[[#This Row],[Operating_Inflows]]-TblCash[[#This Row],[Operating_Outflows]]-TblCash[[#This Row],[Investing_Outflows]] -> 16.2 | L4: =TblCash[[#This Row],[Closing_Cash]]/TblCash[[#This Row],[Operating_Outflows]]+TblCash[[#This Row],[Financing_Outflows]] -> 125.0885
A5: 45383 | B5: 1021.8 | C5: 776.3 | D5: 230.7 | E5: 124.7 | F5: 114.1 | G5: 25.4 | H5: 3339.3 | I5: 3364.7 | J5: =TblCash[[#This Row],[Operating_Inflows]]-TblCash[[#This Row],[Operating_Outflows]]-TblCash[[#This Row],[Investing_Outflows]]+TblCash[[#This Row],[Financing_Inflows]]-TblCash[[#This Row],[Financing_Outflows]] -> 25.4 | K5: =TblCash[[#This Row],[Operating_Inflows]]-TblCash[[#This Row],[Operating_Outflows]]-TblCash[[#This Row],[Investing_Outflows]] -> 14.8 | L5: =TblCash[[#This Row],[Closing_Cash]]/TblCash[[#This Row],[Operating_Outflows]]+TblCash[[#This Row],[Financing_Outflows]] -> 118.43428
A6: 45413 | B6: 881.3 | C6: 708 | D6: 216.2 | E6: 102.6 | F6: 84.6 | G6: -24.9 | H6: 3364.7 | I6: 3339.8 | J6: =TblCash[[#This Row],[Operating_Inflows]]-TblCash[[#This Row],[Operating_Outflows]]-TblCash[[#This Row],[Investing_Outflows]]+TblCash[[#This Row],[Financing_Inflows]]-TblCash[[#This Row],[Financing_Outflows]] -> -24.9 | K6: =TblCash[[#This Row],[Operating_Inflows]]-TblCash[[#This Row],[Operating_Outflows]]-TblCash[[#This Row],[Investing_Outflows]] -> -42.9 | L6: =TblCash[[#This Row],[Closing_Cash]]/TblCash[[#This Row],[Operating_Outflows]]+TblCash[[#This Row],[Financing_Outflows]] -> 89.317232
A7: 45444 | B7: 881.3 | C7: 729.6 | D7: 280.6 | E7: 91 | F7: 109.5 | G7: -147.4 | H7: 3339.8 | I7: 3192.4 | J7: =TblCash[[#This Row],[Operating_Inflows]]-TblCash[[#This Row],[Operating_Outflows]]-TblCash[[#This Row],[Investing_Outflows]]+TblCash[[#This Row],[Financing_Inflows]]-TblCash[[#This Row],[Financing_Outflows]] -> -147.4 | K7: =TblCash[[#This Row],[Operating_Inflows]]-TblCash[[#This Row],[Operating_Outflows]]-TblCash[[#This Row],[Investing_Outflows]] -> -128.9 | L7: =TblCash[[#This Row],[Closing_Cash]]/TblCash[[#This Row],[Operating_Outflows]]+TblCash[[#This Row],[Financing_Outflows]] -> 113.87555
A8: 45474 | B8: 1026.3 | C8: 707.9 | D8: 301.5 | E8: 102.8 | F8: 111.4 | G8: 8.3 | H8: 3192.4 | I8: 3200.7 | J8: =TblCash[[#This Row],[Operating_Inflows]]-TblCash[[#This Row],[Operating_Outflows]]-TblCash[[#This Row],[Investing_Outflows]]+TblCash[[#This Row],[Financing_Inflows]]-TblCash[[#This Row],[Financing_Outflows]] -> 8.3 | K8: =TblCash[[#This Row],[Operating_Inflows]]-TblCash[[#This Row],[Operating_Outflows]]-TblCash[[#This Row],[Investing_Outflows]] -> 16.9 | L8: =TblCash[[#This Row],[Closing_Cash]]/TblCash[[#This Row],[Operating_Outflows]]+TblCash[[#This Row],[Financing_Outflows]] -> 115.9214
A9: 45505 | B9: 961.4 | C9: 879.7 | D9: 296.6 | E9: 40.4 | F9: 99.9 | G9: -274.4 | H9: 3200.7 | I9: 2926.3 | J9: =TblCash[[#This Row],[Operating_Inflows]]-TblCash[[#This Row],[Operating_Outflows]]-TblCash[[#This Row],[Investing_Outflows]]+TblCash[[#This Row],[Financing_Inflows]]-TblCash[[#This Row],[Financing_Outflows]] -> -274.4 | K9: =TblCash[[#This Row],[Operating_Inflows]]-TblCash[[#This Row],[Operating_Outflows]]-TblCash[[#This Row],[Investing_Outflows]] -> -214.9 | L9: =TblCash[[#This Row],[Closing_Cash]]/TblCash[[#This Row],[Operating_Outflows]]+TblCash[[#This Row],[Financing_Outflows]] -> 103.22647
A10: 45536 | B10: 862.4 | C10: 749.1 | D10: 208 | E10: 93.4 | F10: 116 | G10: -117.3 | H10: 2926.3 | I10: 2809 | J10: =TblCash[[#This Row],[Operating_Inflows]]-TblCash[[#This Row],[Operating_Outflows]]-TblCash[[#This Row],[Investing_Outflows]]+TblCash[[#This Row],[Financing_Inflows]]-TblCash[[#This Row],[Financing_Outflows]] -> -117.3 | K10: =TblCash[[#This Row],[Operating_Inflows]]-TblCash[[#This Row],[Operating_Outflows]]-TblCash[[#This Row],[Investing_Outflows]] -> -94.7 | L10: =TblCash[[#This Row],[Closing_Cash]]/TblCash[[#This Row],[Operating_Outflows]]+TblCash[[#This Row],[Financing_Outflows]] -> 119.74983
A11: 45566 | B11: 943.4 | C11: 676 | D11: 234.5 | E11: 110.7 | F11: 130.1 | G11: 13.5 | H11: 2809 | I11: 2822.5 | J11: =TblCash[[#This Row],[Operating_Inflows]]-TblCash[[#This Row],[Operating_Outflows]]-TblCash[[#This Row],[Investing_Outflows]]+TblCash[[#This Row],[Financing_Inflows]]-TblCash[[#This Row],[Financing_Outflows]] -> 13.5 | K11: =TblCash[[#This Row],[Operating_Inflows]]-TblCash[[#This Row],[Operating_Outflows]]-TblCash[[#This Row],[Investing_Outflows]] -> 32.9 | L11: =TblCash[[#This Row],[Closing_Cash]]/TblCash[[#This Row],[Operating_Outflows]]+TblCash[[#This Row],[Financing_Outflows]] -> 134.2753
A12: 45597 | B12: 862.9 | C12: 807.6 | D12: 266.6 | E12: 144.3 | F12: 167.2 | G12: -234.2 | H12: 2822.5 | I12: 2588.3 | J12: =TblCash[[#This Row],[Operating_Inflows]]-TblCash[[#This Row],[Operating_Outflows]]-TblCash[[#This Row],[Investing_Outflows]]+TblCash[[#This Row],[Financing_Inflows]]-TblCash[[#This Row],[Financing_Outflows]] -> -234.2 | K12: =TblCash[[#This Row],[Operating_Inflows]]-TblCash[[#This Row],[Operating_Outflows]]-TblCash[[#This Row],[Investing_Outflows]] -> -211.3 | L12: =TblCash[[#This Row],[Closing_Cash]]/TblCash[[#This Row],[Operating_Outflows]]+TblCash[[#This Row],[Financing_Outflows]] -> 170.40493
A13: 45627 | B13: 862.7 | C13: 664.5 | D13: 298.8 | E13: 84.5 | F13: 124.4 | G13: -140.5 | H13: 2588.3 | I13: 2447.8 | J13: =TblCash[[#This Row],[Operating_Inflows]]-TblCash[[#This Row],[Operating_Outflows]]-TblCash[[#This Row],[Investing_Outflows]]+TblCash[[#This Row],[Financing_Inflows]]-TblCash[[#This Row],[Financing_Outflows]] -> -140.5 | K13: =TblCash[[#This Row],[Operating_Inflows]]-TblCash[[#This Row],[Operating_Outflows]]-TblCash[[#This Row],[Investing_Outflows]] -> -100.6 | L13: =TblCash[[#This Row],[Closing_Cash]]/TblCash[[#This Row],[Operating_Outflows]]+TblCash[[#This Row],[Financing_Outflows]] -> 128.08367
A14: 45658 | B14: 919.4 | C14: 764.6 | D14: 226 | E14: 75.7 | F14: 126.4 | G14: =TblCash[[#This Row],[Operating_Inflows]]-TblCash[[#This Row],[Operating_Outflows]]-TblCash[[#This Row],[Investing_Outflows]]-TblCash[[#This Row],[Financing_Outflows]]+TblCash[[#This Row],[Financing_Inflows]] -> -121.9 | H14: 2447.8 | I14: 2325.9 | J14: =TblCash[[#This Row],[Operating_Inflows]]-TblCash[[#This Row],[Operating_Outflows]]-TblCash[[#This Row],[Investing_Outflows]]+TblCash[[#This Row],[Financing_Inflows]]-TblCash[[#This Row],[Financing_Outflows]] -> -121.9 | K14: =TblCash[[#This Row],[Operating_Inflows]]-TblCash[[#This Row],[Operating_Outflows]]-TblCash[[#This Row],[Investing_Outflows]] -> -71.2 | L14: =TblCash[[#This Row],[Closing_Cash]]/TblCash[[#This Row],[Operating_Outflows]]+TblCash[[#This Row],[Financing_Outflows]] -> 129.44198
A15: 45689 | B15: 746.9 | C15: 612.8 | D15: 240.7 | E15: 84.9 | F15: 118.1 | G15: -139.8 | H15: 2325.9 | I15: 2186.1 | J15: =TblCash[[#This Row],[Operating_Inflows]]-TblCash[[#This Row],[Operating_Outflows]]-TblCash[[#This Row],[Investing_Outflows]]+TblCash[[#This Row],[Financing_Inflows]]-TblCash[[#This Row],[Financing_Outflows]] -> -139.8 | K15: =TblCash[[#This Row],[Operating_Inflows]]-TblCash[[#This Row],[Operating_Outflows]]-TblCash[[#This Row],[Investing_Outflows]] -> -106.6 | L15: =TblCash[[#This Row],[Closing_Cash]]/TblCash[[#This Row],[Operating_Outflows]]+TblCash[[#This Row],[Financing_Outflows]] -> 121.6674
A16: 45717 | B16: 762 | C16: 657 | D16: 194.7 | E16: 127.5 | F16: 72 | G16: -34.2 | H16: 2186.1 | I16: 2151.9 | J16: =TblCash[[#This Row],[Operating_Inflows]]-TblCash[[#This Row],[Operating_Outflows]]-TblCash[[#This Row],[Investing_Outflows]]+TblCash[[#This Row],[Financing_Inflows]]-TblCash[[#This Row],[Financing_Outflows]] -> -34.2 | K16: =TblCash[[#This Row],[Operating_Inflows]]-TblCash[[#This Row],[Operating_Outflows]]-TblCash[[#This Row],[Investing_Outflows]] -> -89.7 | L16: =TblCash[[#This Row],[Closing_Cash]]/TblCash[[#This Row],[Operating_Outflows]]+TblCash[[#This Row],[Financing_Outflows]] -> 75.275342
A17: 45748 | B17: 855 | C17: 763.8 | D17: 190.2 | E17: 109.9 | F17: 119.3 | G17: -108.4 | H17: 2151.9 | I17: 2043.5 | J17: =TblCash[[#This Row],[Operating_Inflows]]-TblCash[[#This Row],[Operating_Outflows]]-TblCash[[#This Row],[Investing_Outflows]]+TblCash[[#This Row],[Financing_Inflows]]-TblCash[[#This Row],[Financing_Outflows]] -> -108.4 | K17: =TblCash[[#This Row],[Operating_Inflows]]-TblCash[[#This Row],[Operating_Outflows]]-TblCash[[#This Row],[Investing_Outflows]] -> -99 | L17: =TblCash[[#This Row],[Closing_Cash]]/TblCash[[#This Row],[Operating_Outflows]]+TblCash[[#This Row],[Financing_Outflows]] -> 121.97544
A18: 45778 | B18: 819 | C18: 801.7 | D18: 290.6 | E18: 84.1 | F18: 121.5 | G18: -310.7 | H18: 2043.5 | I18: 1732.8 | J18: =TblCash[[#This Row],[Operating_Inflows]]-TblCash[[#This Row],[Operating_Outflows]]-TblCash[[#This Row],[Investing_Outflows]]+TblCash[[#This Row],[Financing_Inflows]]-TblCash[[#This Row],[Financing_Outflows]] -> -310.7 | K18: =TblCash[[#This Row],[Operating_Inflows]]-TblCash[[#This Row],[Operating_Outflows]]-TblCash[[#This Row],[Investing_Outflows]] -> -273.3 | L18: =TblCash[[#This Row],[Closing_Cash]]/TblCash[[#This Row],[Operating_Outflows]]+TblCash[[#This Row],[Financing_Outflows]] -> 123.66141
A19: 45809 | B19: 925.1 | C19: 762 | D19: 317.8 | E19: 115.4 | F19: 181.6 | G19: -220.9 | H19: 1732.8 | I19: 1511.9 | J19: =TblCash[[#This Row],[Operating_Inflows]]-TblCash[[#This Row],[Operating_Outflows]]-TblCash[[#This Row],[Investing_Outflows]]+TblCash[[#This Row],[Financing_Inflows]]-TblCash[[#This Row],[Financing_Outflows]] -> -220.9 | K19: =TblCash[[#This Row],[Operating_Inflows]]-TblCash[[#This Row],[Operating_Outflows]]-TblCash[[#This Row],[Investing_Outflows]] -> -154.7 | L19: =TblCash[[#This Row],[Closing_Cash]]/TblCash[[#This Row],[Operating_Outflows]]+TblCash[[#This Row],[Financing_Outflows]] -> 183.58412
A20: 45839 | B20: 827.4 | C20: 741.9 | D20: 246.4 | E20: 102.9 | F20: 115.2 | G20: -173.2 | H20: 1511.9 | I20: 1338.7 | J20: =TblCash[[#This Row],[Operating_Inflows]]-TblCash[[#This Row],[Operating_Outflows]]-TblCash[[#This Row],[Investing_Outflows]]+TblCash[[#This Row],[Financing_Inflows]]-TblCash[[#This Row],[Financing_Outflows]] -> -173.2 | K20: =TblCash[[#This Row],[Operating_Inflows]]-TblCash[[#This Row],[Operating_Outflows]]-TblCash[[#This Row],[Investing_Outflows]] -> -160.9 | L20: =TblCash[[#This Row],[Closing_Cash]]/TblCash[[#This Row],[Operating_Outflows]]+TblCash[[#This Row],[Financing_Outflows]] -> 117.00442
A21: 45870 | B21: 787 | C21: 728.9 | D21: 300.2 | E21: 129.1 | F21: 127.5 | G21: -240.5 | H21: 1338.7 | I21: 1098.2 | J21: =TblCash[[#This Row],[Operating_Inflows]]-TblCash[[#This Row],[Operating_Outflows]]-TblCash[[#This Row],[Investing_Outflows]]+TblCash[[#This Row],[Financing_Inflows]]-TblCash[[#This Row],[Financing_Outflows]] -> -240.5 | K21: =TblCash[[#This Row],[Operating_Inflows]]-TblCash[[#This Row],[Operating_Outflows]]-TblCash[[#This Row],[Investing_Outflows]] -> -242.1 | L21: =TblCash[[#This Row],[Closing_Cash]]/TblCash[[#This Row],[Operating_Outflows]]+TblCash[[#This Row],[Financing_Outflows]] -> 129.00665
A22: 45901 | B22: 1017.3 | C22: 646.5 | D22: 268.1 | E22: 78.9 | F22: 119.1 | G22: 62.5 | H22: 1098.2 | I22: 1160.7 | J22: =TblCash[[#This Row],[Operating_Inflows]]-TblCash[[#This Row],[Operating_Outflows]]-TblCash[[#This Row],[Investing_Outflows]]+TblCash[[#This Row],[Financing_Inflows]]-TblCash[[#This Row],[Financing_Outflows]] -> 62.5 | K22: =TblCash[[#This Row],[Operating_Inflows]]-TblCash[[#This Row],[Operating_Outflows]]-TblCash[[#This Row],[Investing_Outflows]] -> 102.7 | L22: =TblCash[[#This Row],[Closing_Cash]]/TblCash[[#This Row],[Operating_Outflows]]+TblCash[[#This Row],[Financing_Outflows]] -> 120.89536
A23: 45931 | B23: 881.9 | C23: 699.6 | D23: 217.7 | E23: 90.2 | F23: 90.8 | G23: -36 | H23: 1160.7 | I23: 1124.7 | J23: =TblCash[[#This Row],[Operating_Inflows]]-TblCash[[#This Row],[Operating_Outflows]]-TblCash[[#This Row],[Investing_Outflows]]+TblCash[[#This Row],[Financing_Inflows]]-TblCash[[#This Row],[Financing_Outflows]] -> -36 | K23: =TblCash[[#This Row],[Operating_Inflows]]-TblCash[[#This Row],[Operating_Outflows]]-TblCash[[#This Row],[Investing_Outflows]] -> -35.4 | L23: =TblCash[[#This Row],[Closing_Cash]]/TblCash[[#This Row],[Operating_Outflows]]+TblCash[[#This Row],[Financing_Outflows]] -> 92.407633
A24: 45962 | B24: 905.4 | C24: 717.8 | D24: 268.1 | E24: 88.2 | F24: 148.6 | G24: -140.9 | H24: 1124.7 | I24: 983.8 | J24: =TblCash[[#This Row],[Operating_Inflows]]-TblCash[[#This Row],[Operating_Outflows]]-TblCash[[#This Row],[Investing_Outflows]]+TblCash[[#This Row],[Financing_Inflows]]-TblCash[[#This Row],[Financing_Outflows]] -> -140.9 | K24: =TblCash[[#This Row],[Operating_Inflows]]-TblCash[[#This Row],[Operating_Outflows]]-TblCash[[#This Row],[Investing_Outflows]] -> -80.5 | L24: =TblCash[[#This Row],[Closing_Cash]]/TblCash[[#This Row],[Operating_Outflows]]+TblCash[[#This Row],[Financing_Outflows]] -> 149.97058
A25: 45992 | B25: 993 | C25: 824 | D25: 326.9 | E25: 56.1 | F25: 138.8 | G25: -240.6 | H25: 983.8 | I25: 743.2 | J25: =TblCash[[#This Row],[Operating_Inflows]]-TblCash[[#This Row],[Operating_Outflows]]-TblCash[[#This Row],[Investing_Outflows]]+TblCash[[#This Row],[Financing_Inflows]]-TblCash[[#This Row],[Financing_Outflows]] -> -240.6 | K25: =TblCash[[#This Row],[Operating_Inflows]]-TblCash[[#This Row],[Operating_Outflows]]-TblCash[[#This Row],[Investing_Outflows]] -> -157.9 | L25: =TblCash[[#This Row],[Closing_Cash]]/TblCash[[#This Row],[Operating_Outflows]]+TblCash[[#This Row],[Financing_Outflows]] -> 139.70194

Sheet Balance_Components
A1: Period | B1: Accounts_Receivable | C1: Accounts_Payable | D1: Inventory | E1: Cash | F1: Short_Term_Debt | G1: Current_Assets | H1: Current_Liabilities | I1: Revenue_TTM | J1: COGS_TTM | K1: Liquidity_Ratio | L1: Quick Ratio | M1: DSO_days | N1: DPO_days | O1: DIO_days | P1: CCC_days
A2: 45382 | B2: 4258 | C2: 3920 | D2: 2183 | E2: 4265 | F2: 3064 | G2: 14513 | H2: 11102 | I2: 11100 | J2: 7992 | K2: =ROUND(TblForecast[[#This Row],[Current_Assets]]/TblForecast[[#This Row],[Current_Liabilities]],2) -> 1.31 | L2: =ROUND((TblForecast[[#This Row],[Cash]]+TblForecast[[#This Row],[Accounts_Receivable]])/TblForecast[[#This Row],[Current_Liabilities]],2) -> 0.77 | M2: =ROUND(TblForecast[[#This Row],[Accounts_Receivable]]/TblForecast[[#This Row],[Revenue_TTM]]*365,1) -> 140 | N2: =ROUND(TblForecast[[#This Row],[Accounts_Payable]]/TblForecast[[#This Row],[COGS_TTM]]*365,1) -> 179 | O2: =ROUND(TblForecast[[#This Row],[Inventory]]/TblForecast[[#This Row],[COGS_TTM]]*365,1) -> 99.7 | P2: =ROUND(TblForecast[[#This Row],[DSO_days]]+TblForecast[[#This Row],[DIO_days]]-TblForecast[[#This Row],[DPO_days]],1) -> 60.7
A3: 45473 | B3: 3918 | C3: 3799 | D3: 2252 | E3: 4395 | F3: 3246 | G3: 15394 | H3: 10899 | I3: 11450 | J3: 8244 | K3: =ROUND(TblForecast[[#This Row],[Current_Assets]]/TblForecast[[#This Row],[Current_Liabilities]],2) -> 1.41 | L3: =ROUND((TblForecast[[#This Row],[Cash]]+TblForecast[[#This Row],[Accounts_Receivable]])/TblForecast[[#This Row],[Current_Liabilities]],2) -> 0.76 | M3: =ROUND(TblForecast[[#This Row],[Accounts_Receivable]]/TblForecast[[#This Row],[Revenue_TTM]]*365,1) -> 124.9 | N3: =ROUND(TblForecast[[#This Row],[Accounts_Payable]]/TblForecast[[#This Row],[COGS_TTM]]*365,1) -> 168.2 | O3: =ROUND(TblForecast[[#This Row],[Inventory]]/TblForecast[[#This Row],[COGS_TTM]]*365,1) -> 99.7 | P3: =ROUND(TblForecast[[#This Row],[DSO_days]]+TblForecast[[#This Row],[DIO_days]]-TblForecast[[#This Row],[DPO_days]],1) -> 56.4
A4: 45565 | B4: 4381 | C4: 3590 | D4: 2422 | E4: 3891 | F4: 3259 | G4: 15579 | H4: 10844 | I4: 11700 | J4: 8424 | K4: =ROUND(TblForecast[[#This Row],[Current_Assets]]/TblForecast[[#This Row],[Current_Liabilities]],2) -> 1.44 | L4: =ROUND((TblForecast[[#This Row],[Cash]]+TblForecast[[#This Row],[Accounts_Receivable]])/TblForecast[[#This Row],[Current_Liabilities]],2) -> 0.76 | M4: =ROUND(TblForecast[[#This Row],[Accounts_Receivable]]/TblForecast[[#This Row],[Revenue_TTM]]*365,1) -> 136.7 | N4: =ROUND(TblForecast[[#This Row],[Accounts_Payable]]/TblForecast[[#This Row],[COGS_TTM]]*365,1) -> 155.5 | O4: =ROUND(TblForecast[[#This Row],[Inventory]]/TblForecast[[#This Row],[COGS_TTM]]*365,1) -> 104.9 | P4: =ROUND(TblForecast[[#This Row],[DSO_days]]+TblForecast[[#This Row],[DIO_days]]-TblForecast[[#This Row],[DPO_days]],1) -> 86.1
A5: 45657 | B5: 3820 | C5: 3914 | D5: 2115 | E5: 3870 | F5: 3057 | G5: 14590 | H5: 10874 | I5: 11950 | J5: 8604 | K5: =ROUND(TblForecast[[#This Row],[Current_Assets]]/TblForecast[[#This Row],[Current_Liabilities]],2) -> 1.34 | L5: =ROUND((TblForecast[[#This Row],[Cash]]+TblForecast[[#This Row],[Accounts_Receivable]])/TblForecast[[#This Row],[Current_Liabilities]],2) -> 0.71 | M5: =ROUND(TblForecast[[#This Row],[Accounts_Receivable]]/TblForecast[[#This Row],[Revenue_TTM]]*365,1) -> 116.7 | N5: =ROUND(TblForecast[[#This Row],[Accounts_Payable]]/TblForecast[[#This Row],[COGS_TTM]]*365,1) -> 166 | O5: =ROUND(TblForecast[[#This Row],[Inventory]]/TblForecast[[#This Row],[COGS_TTM]]*365,1) -> 89.7 | P5: =ROUND(TblForecast[[#This Row],[DSO_days]]+TblForecast[[#This Row],[DIO_days]]-TblForecast[[#This Row],[DPO_days]],1) -> 40.4
A6: 45747 | B6: 4217 | C6: 3688 | D6: 2334 | E6: 4330 | F6: 3573 | G6: 15482 | H6: 11169 | I6: 12200 | J6: 8784 | K6: =ROUND(TblForecast[[#This Row],[Current_Assets]]/TblForecast[[#This Row],[Current_Liabilities]],2) -> 1.39 | L6: =ROUND((TblForecast[[#This Row],[Cash]]+TblForecast[[#This Row],[Accounts_Receivable]])/TblForecast[[#This Row],[Current_Liabilities]],2) -> 0.77 | M6: =ROUND(TblForecast[[#This Row],[Accounts_Receivable]]/TblForecast[[#This Row],[Revenue_TTM]]*365,1) -> 126.2 | N6: =ROUND(TblForecast[[#This Row],[Accounts_Payable]]/TblForecast[[#This Row],[COGS_TTM]]*365,1) -> 153.2 | O6: =ROUND(TblForecast[[#This Row],[Inventory]]/TblForecast[[#This Row],[COGS_TTM]]*365,1) -> 97 | P6: =ROUND(TblForecast[[#This Row],[DSO_days]]+TblForecast[[#This Row],[DIO_days]]-TblForecast[[#This Row],[DPO_days]],1) -> 70
A7: 45838 | B7: 4538 | C7: 3995 | D7: 2496 | E7: 4274 | F7: 3295 | G7: 15206 | H7: 11336 | I7: 12450 | J7: 8964 | K7: =ROUND(TblForecast[[#This Row],[Current_Assets]]/TblForecast[[#This Row],[Current_Liabilities]],2) -> 1.34 | L7: =ROUND((TblForecast[[#This Row],[Cash]]+TblForecast[[#This Row],[Accounts_Receivable]])/TblForecast[[#This Row],[Current_Liabilities]],2) -> 0.78 | M7: =ROUND(TblForecast[[#This Row],[Accounts_Receivable]]/TblForecast[[#This Row],[Revenue_TTM]]*365,1) -> 133 | N7: =ROUND(TblForecast[[#This Row],[Accounts_Payable]]/TblForecast[[#This Row],[COGS_TTM]]*365,1) -> 162.7 | O7: =ROUND(TblForecast[[#This Row],[Inventory]]/TblForecast[[#This Row],[COGS_TTM]]*365,1) -> 101.6 | P7: =ROUND(TblForecast[[#This Row],[DSO_days]]+TblForecast[[#This Row],[DIO_days]]-TblForecast[[#This Row],[DPO_days]],1) -> 71.9
A8: 45930 | B8: 3902 | C8: 3716 | D8: 2059 | E8: 4263 | F8: 2962 | G8: 15411 | H8: 11311 | I8: 12600 | J8: 9072 | K8: =ROUND(TblForecast[[#This Row],[Current_Assets]]/TblForecast[[#This Row],[Current_Liabilities]],2) -> 1.36 | L8: =ROUND((TblForecast[[#This Row],[Cash]]+TblForecast[[#This Row],[Accounts_Receivable]])/TblForecast[[#This Row],[Current_Liabilities]],2) -> 0.72 | M8: =ROUND(TblForecast[[#This Row],[Accounts_Receivable]]/TblForecast[[#This Row],[Revenue_TTM]]*365,1) -> 113 | N8: =ROUND(TblForecast[[#This Row],[Accounts_Payable]]/TblForecast[[#This Row],[COGS_TTM]]*365,1) -> 149.5 | O8: =ROUND(TblForecast[[#This Row],[Inventory]]/TblForecast[[#This Row],[COGS_TTM]]*365,1) -> 82.8 | P8: =ROUND(TblForecast[[#This Row],[DSO_days]]+TblForecast[[#This Row],[DIO_days]]-TblForecast[[#This Row],[DPO_days]],1) -> 46.3
A9: 46022 | B9: 3987 | C9: 4210 | D9: 2328 | E9: 4287 | F9: 3331 | G9: 15948 | H9: 11531 | I9: 12800 | J9: 9216 | K9: =ROUND(TblForecast[[#This Row],[Current_Assets]]/TblForecast[[#This Row],[Current_Liabilities]],2) -> 1.38 | L9: =ROUND((TblForecast[[#This Row],[Cash]]+TblForecast[[#This Row],[Accounts_Receivable]])/TblForecast[[#This Row],[Current_Liabilities]],2) -> 0.72 | M9: =ROUND(TblForecast[[#This Row],[Accounts_Receivable]]/TblForecast[[#This Row],[Revenue_TTM]]*365,1) -> 113.7 | N9: =ROUND(TblForecast[[#This Row],[Accounts_Payable]]/TblForecast[[#This Row],[COGS_TTM]]*365,1) -> 166.7 | O9: =ROUND(TblForecast[[#This Row],[Inventory]]/TblForecast[[#This Row],[COGS_TTM]]*365,1) -> 92.2 | P9: =ROUND(TblForecast[[#This Row],[DSO_days]]+TblForecast[[#This Row],[DIO_days]]-TblForecast[[#This Row],[DPO_days]],1) -> 39.2

Sheet Scenarios_Forecast
A1: Scenario | B1: Revenue_Growth_% | C1: COGS_Growth_% | D1: Interest_Rate_% | E1: CapEx_€M
A2: Base | B2: 3 | C2: 2.5 | D2: 3 | E2: 1600
A3: Optimistic | B3: 5 | C3: 2 | D3: 2.5 | E3: 2000
A4: Pessimistic | B4: 1 | C4: 3 | D4: 4 | E4: 1200

Sheet Controls
C3: Active scenario | E3: FX_Shock_% | F3: 5
C4: Base
B6: Revenue_Growth_% | C6: =_xlfn.XLOOKUP(SelScenario,TblScenarios[Scenario],TblScenarios[Revenue_Growth_%]) -> 3
B7: COGS_Growth_% | C7: =_xlfn.XLOOKUP(SelScenario,TblScenarios[Scenario],TblScenarios[COGS_Growth_%]) -> 2.5
B8: Interest_Rate_% | C8: =_xlfn.XLOOKUP(SelScenario,TblScenarios[Scenario],TblScenarios[Interest_Rate_%]) -> 3
B9: CapEx_€M | C9: =_xlfn.XLOOKUP(SelScenario,TblScenarios[Scenario],TblScenarios[CapEx_€M]) -> 1600

Sheet Forecasts
A1: Period | B1: Operating_Inflows | C1: Operating_Outflows | D1: Investing_Outflows | E1: Financing_Inflows | F1: Financing_Outflows | G1: forecast_net | H1: forecast_opening | I1: forecast_closing | J1: FCF | K1: CC_Ratio | L1: Liquidity Buffer | M1: Interest_Coverage | N1: operating_Margin % | O1: EBITDA/EBIT_PROXY | P1: INTEREST PROXY
A2: 45658 | B2: 919.4 | C2: 764.6 | D2: 226 | E2: 75.7 | F2: 126.4 | G2: =Table7[[#This Row],[Operating_Inflows]]-Table7[[#This Row],[Operating_Outflows]]-Table7[[#This Row],[Investing_Outflows]]+Table7[[#This Row],[Financing_Inflows]]-Table7[[#This Row],[Financing_Outflows]] -> -121.9 | H2: 2447.8 | I2: 2325.9 | J2: =Table7[[#This Row],[Operating_Inflows]]-Table7[[#This Row],[Operating_Outflows]]-Table7[[#This Row],[Investing_Outflows]] -> -71.2 | K2: =Table7[[#This Row],[FCF]]/Table7[[#This Row],[EBITDA/EBIT_PROXY]] -> -0.45994832 | L2: =Table7[[#This Row],[forecast_closing]]/(Table7[[#This Row],[Operating_Outflows]]/12) -> 36.503793 | M2: =Table7[[#This Row],[EBITDA/EBIT_PROXY]]/Table7[[#This Row],[INTEREST PROXY]] -> 3.0617089 | N2: =Table7[[#This Row],[EBITDA/EBIT_PROXY]]/Table7[[#This Row],[Operating_Inflows]] -> 0.16837068 | O2: =Table7[[#This Row],[Operating_Inflows]]-Table7[[#This Row],[Operating_Outflows]] -> 154.8 | P2: =0.4*Table7[[#This Row],[Financing_Outflows]] -> 50.56
A3: 45689 | B3: 746.9 | C3: 612.8 | D3: 240.7 | E3: 84.9 | F3: 118.1 | G3: =Table7[[#This Row],[Operating_Inflows]]-Table7[[#This Row],[Operating_Outflows]]-Table7[[#This Row],[Investing_Outflows]]+Table7[[#This Row],[Financing_Inflows]]-Table7[[#This Row],[Financing_Outflows]] -> -139.8 | H3: 2325.9 | I3: 2186.1 | J3: =Table7[[#This Row],[Operating_Inflows]]-Table7[[#This Row],[Operating_Outflows]]-Table7[[#This Row],[Investing_Outflows]] -> -106.6 | K3: =Table7[[#This Row],[FCF]]/Table7[[#This Row],[EBITDA/EBIT_PROXY]] -> -0.79492916 | L3: =Table7[[#This Row],[forecast_closing]]/(Table7[[#This Row],[Operating_Outflows]]/12) -> 42.808747 | M3: =Table7[[#This Row],[EBITDA/EBIT_PROXY]]/Table7[[#This Row],[INTEREST PROXY]] -> 2.838696 | N3: =Table7[[#This Row],[EBITDA/EBIT_PROXY]]/Table7[[#This Row],[Operating_Inflows]] -> 0.17954211 | O3: =Table7[[#This Row],[Operating_Inflows]]-Table7[[#This Row],[Operating_Outflows]] -> 134.1 | P3: =0.4*Table7[[#This Row],[Financing_Outflows]] -> 47.24
A4: 45717 | B4: 762 | C4: 657 | D4: 194.7 | E4: 127.5 | F4: 72 | G4: =Table7[[#This Row],[Operating_Inflows]]-Table7[[#This Row],[Operating_Outflows]]-Table7[[#This Row],[Investing_Outflows]]+Table7[[#This Row],[Financing_Inflows]]-Table7[[#This Row],[Financing_Outflows]] -> -34.2 | H4: 2186.1 | I4: 2151.9 | J4: =Table7[[#This Row],[Operating_Inflows]]-Table7[[#This Row],[Operating_Outflows]]-Table7[[#This Row],[Investing_Outflows]] -> -89.7 | K4: =Table7[[#This Row],[FCF]]/Table7[[#This Row],[EBITDA/EBIT_PROXY]] -> -0.85428571 | L4: =Table7[[#This Row],[forecast_closing]]/(Table7[[#This Row],[Operating_Outflows]]/12) -> 39.30411 | M4: =Table7[[#This Row],[EBITDA/EBIT_PROXY]]/Table7[[#This Row],[INTEREST PROXY]] -> 3.6458333 | N4: =Table7[[#This Row],[EBITDA/EBIT_PROXY]]/Table7[[#This Row],[Operating_Inflows]] -> 0.13779528 | O4: =Table7[[#This Row],[Operating_Inflows]]-Table7[[#This Row],[Operating_Outflows]] -> 105 | P4: =0.4*Table7[[#This Row],[Financing_Outflows]] -> 28.8
A5: 45748 | B5: 855 | C5: 763.8 | D5: 190.2 | E5: 109.9 | F5: 119.3 | G5: =Table7[[#This Row],[Operating_Inflows]]-Table7[[#This Row],[Operating_Outflows]]-Table7[[#This Row],[Investing_Outflows]]+Table7[[#This Row],[Financing_Inflows]]-Table7[[#This Row],[Financing_Outflows]] -> -108.4 | H5: 2151.9 | I5: 2043.5 | J5: =Table7[[#This Row],[Operating_Inflows]]-Table7[[#This Row],[Operating_Outflows]]-Table7[[#This Row],[Investing_Outflows]] -> -99 | K5: =Table7[[#This Row],[FCF]]/Table7[[#This Row],[EBITDA/EBIT_PROXY]] -> -1.0855263 | L5: =Table7[[#This Row],[forecast_closing]]/(Table7[[#This Row],[Operating_Outflows]]/12) -> 32.105263 | M5: =Table7[[#This Row],[EBITDA/EBIT_PROXY]]/Table7[[#This Row],[INTEREST PROXY]] -> 1.9111484 | N5: =Table7[[#This Row],[EBITDA/EBIT_PROXY]]/Table7[[#This Row],[Operating_Inflows]] -> 0.10666667 | O5: =Table7[[#This Row],[Operating_Inflows]]-Table7[[#This Row],[Operating_Outflows]] -> 91.2 | P5: =0.4*Table7[[#This Row],[Financing_Outflows]] -> 47.72
A6: 45778 | B6: 819 | C6: 801.7 | D6: 290.6 | E6: 84.1 | F6: 121.5 | G6: =Table7[[#This Row],[Operating_Inflows]]-Table7[[#This Row],[Operating_Outflows]]-Table7[[#This Row],[Investing_Outflows]]+Table7[[#This Row],[Financing_Inflows]]-Table7[[#This Row],[Financing_Outflows]] -> -310.7 | H6: 2043.5 | I6: 1732.8 | J6: =Table7[[#This Row],[Operating_Inflows]]-Table7[[#This Row],[Operating_Outflows]]-Table7[[#This Row],[Investing_Outflows]] -> -273.3 | K6: =Table7[[#This Row],[FCF]]/Table7[[#This Row],[EBITDA/EBIT_PROXY]] -> -15.797688 | L6: =Table7[[#This Row],[forecast_closing]]/(Table7[[#This Row],[Operating_Outflows]]/12) -> 25.936884 | M6: =Table7[[#This Row],[EBITDA/EBIT_PROXY]]/Table7[[#This Row],[INTEREST PROXY]] -> 0.35596708 | N6: =Table7[[#This Row],[EBITDA/EBIT_PROXY]]/Table7[[#This Row],[Operating_Inflows]] -> 0.021123321 | O6: =Table7[[#This Row],[Operating_Inflows]]-Table7[[#This Row],[Operating_Outflows]] -> 17.3 | P6: =0.4*Table7[[#This Row],[Financing_Outflows]] -> 48.6
A7: 45809 | B7: 925.1 | C7: 762 | D7: 317.8 | E7: 115.4 | F7: 181.6 | G7: =Table7[[#This Row],[Operating_Inflows]]-Table7[[#This Row],[Operating_Outflows]]-Table7[[#This Row],[Investing_Outflows]]+Table7[[#This Row],[Financing_Inflows]]-Table7[[#This Row],[Financing_Outflows]] -> -220.9 | H7: 1732.8 | I7: 1511.9 | J7: =Table7[[#This Row],[Operating_Inflows]]-Table7[[#This Row],[Operating_Outflows]]-Table7[[#This Row],[Investing_Outflows]] -> -154.7 | K7: =Table7[[#This Row],[FCF]]/Table7[[#This Row],[EBITDA/EBIT_PROXY]] -> -0.94849785 | L7: =Table7[[#This Row],[forecast_closing]]/(Table7[[#This Row],[Operating_Outflows]]/12) -> 23.809449 | M7: =Table7[[#This Row],[EBITDA/EBIT_PROXY]]/Table7[[#This Row],[INTEREST PROXY]] -> 2.2453194 | N7: =Table7[[#This Row],[EBITDA/EBIT_PROXY]]/Table7[[#This Row],[Operating_Inflows]] -> 0.17630526 | O7: =Table7[[#This Row],[Operating_Inflows]]-Table7[[#This Row],[Operating_Outflows]] -> 163.1 | P7: =0.4*Table7[[#This Row],[Financing_Outflows]] -> 72.64
A8: 45839 | B8: 827.4 | C8: 741.9 | D8: 246.4 | E8: 102.9 | F8: 115.2 | G8: =Table7[[#This Row],[Operating_Inflows]]-Table7[[#This Row],[Operating_Outflows]]-Table7[[#This Row],[Investing_Outflows]]+Table7[[#This Row],[Financing_Inflows]]-Table7[[#This Row],[Financing_Outflows]] -> -173.2 | H8: 1511.9 | I8: 1338.7 | J8: =Table7[[#This Row],[Operating_Inflows]]-Table7[[#This Row],[Operating_Outflows]]-Table7[[#This Row],[Investing_Outflows]] -> -160.9 | K8: =Table7[[#This Row],[FCF]]/Table7[[#This Row],[EBITDA/EBIT_PROXY]] -> -1.8818713 | L8: =Table7[[#This Row],[forecast_closing]]/(Table7[[#This Row],[Operating_Outflows]]/12) -> 21.653053 | M8: =Table7[[#This Row],[EBITDA/EBIT_PROXY]]/Table7[[#This Row],[INTEREST PROXY]] -> 1.8554687 | N8: =Table7[[#This Row],[EBITDA/EBIT_PROXY]]/Table7[[#This Row],[Operating_Inflows]] -> 0.10333575 | O8: =Table7[[#This Row],[Operating_Inflows]]-Table7[[#This Row],[Operating_Outflows]] -> 85.5 | P8: =0.4*Table7[[#This Row],[Financing_Outflows]] -> 46.08
A9: 45870 | B9: 787 | C9: 728.9 | D9: 300.2 | E9: 129.1 | F9: 127.5 | G9: =Table7[[#This Row],[Operating_Inflows]]-Table7[[#This Row],[Operating_Outflows]]-Table7[[#This Row],[Investing_Outflows]]+Table7[[#This Row],[Financing_Inflows]]-Table7[[#This Row],[Financing_Outflows]] -> -240.5 | H9: 1338.7 | I9: 1098.2 | J9: =Table7[[#This Row],[Operating_Inflows]]-Table7[[#This Row],[Operating_Outflows]]-Table7[[#This Row],[Investing_Outflows]] -> -242.1 | K9: =Table7[[#This Row],[FCF]]/Table7[[#This Row],[EBITDA/EBIT_PROXY]] -> -4.1669535 | L9: =Table7[[#This Row],[forecast_closing]]/(Table7[[#This Row],[Operating_Outflows]]/12) -> 18.079846 | M9: =Table7[[#This Row],[EBITDA/EBIT_PROXY]]/Table7[[#This Row],[INTEREST PROXY]] -> 1.1392157 | N9: =Table7[[#This Row],[EBITDA/EBIT_PROXY]]/Table7[[#This Row],[Operating_Inflows]] -> 0.073824651 | O9: =Table7[[#This Row],[Operating_Inflows]]-Table7[[#This Row],[Operating_Outflows]] -> 58.1 | P9: =0.4*Table7[[#This Row],[Financing_Outflows]] -> 51
A10: 45901 | B10: 1017.3 | C10: 646.5 | D10: 268.1 | E10: 78.9 | F10: 119.1 | G10: =Table7[[#This Row],[Operating_Inflows]]-Table7[[#This Row],[Operating_Outflows]]-Table7[[#This Row],[Investing_Outflows]]+Table7[[#This Row],[Financing_Inflows]]-Table7[[#This Row],[Financing_Outflows]] -> 62.5 | H10: 1098.2 | I10: 1160.7 | J10: =Table7[[#This Row],[Operating_Inflows]]-Table7[[#This Row],[Operating_Outflows]]-Table7[[#This Row],[Investing_Outflows]] -> 102.7 | K10: =Table7[[#This Row],[FCF]]/Table7[[#This Row],[EBITDA/EBIT_PROXY]] -> 0.27696872 | L10: =Table7[[#This Row],[forecast_closing]]/(Table7[[#This Row],[Operating_Outflows]]/12) -> 21.544316 | M10: =Table7[[#This Row],[EBITDA/EBIT_PROXY]]/Table7[[#This Row],[INTEREST PROXY]] -> 7.7833753 | N10: =Table7[[#This Row],[EBITDA/EBIT_PROXY]]/Table7[[#This Row],[Operating_Inflows]] -> 0.36449425 | O10: =Table7[[#This Row],[Operating_Inflows]]-Table7[[#This Row],[Operating_Outflows]] -> 370.8 | P10: =0.4*Table7[[#This Row],[Financing_Outflows]] -> 47.64
A11: 45931 | B11: 881.9 | C11: 699.6 | D11: 217.7 | E11: 90.2 | F11: 90.8 | G11: =Table7[[#This Row],[Operating_Inflows]]-Table7[[#This Row],[Operating_Outflows]]-Table7[[#This Row],[Investing_Outflows]]+Table7[[#This Row],[Financing_Inflows]]-Table7[[#This Row],[Financing_Outflows]] -> -36 | H11: 1160.7 | I11: 1124.7 | J11: =Table7[[#This Row],[Operating_Inflows]]-Table7[[#This Row],[Operating_Outflows]]-Table7[[#This Row],[Investing_Outflows]] -> -35.4 | K11: =Table7[[#This Row],[FCF]]/Table7[[#This Row],[EBITDA/EBIT_PROXY]] -> -0.19418541 | L11: =Table7[[#This Row],[forecast_closing]]/(Table7[[#This Row],[Operating_Outflows]]/12) -> 19.291595 | M11: =Table7[[#This Row],[EBITDA/EBIT_PROXY]]/Table7[[#This Row],[INTEREST PROXY]] -> 5.0192731 | N11: =Table7[[#This Row],[EBITDA/EBIT_PROXY]]/Table7[[#This Row],[Operating_Inflows]] -> 0.20671278 | O11: =Table7[[#This Row],[Operating_Inflows]]-Table7[[#This Row],[Operating_Outflows]] -> 182.3 | P11: =0.4*Table7[[#This Row],[Financing_Outflows]] -> 36.32
A12: 45962 | B12: 905.4 | C12: 717.8 | D12: 268.1 | E12: 88.2 | F12: 148.6 | G12: =Table7[[#This Row],[Operating_Inflows]]-Table7[[#This Row],[Operating_Outflows]]-Table7[[#This Row],[Investing_Outflows]]+Table7[[#This Row],[Financing_Inflows]]-Table7[[#This Row],[Financing_Outflows]] -> -140.9 | H12: 1124.7 | I12: 983.8 | J12: =Table7[[#This Row],[Operating_Inflows]]-Table7[[#This Row],[Operating_Outflows]]-Table7[[#This Row],[Investing_Outflows]] -> -80.5 | K12: =Table7[[#This Row],[FCF]]/Table7[[#This Row],[EBITDA/EBIT_PROXY]] -> -0.42910448 | L12: =Table7[[#This Row],[forecast_closing]]/(Table7[[#This Row],[Operating_Outflows]]/12) -> 16.446921 | M12: =Table7[[#This Row],[EBITDA/EBIT_PROXY]]/Table7[[#This Row],[INTEREST PROXY]] -> 3.1561238 | N12: =Table7[[#This Row],[EBITDA/EBIT_PROXY]]/Table7[[#This Row],[Operating_Inflows]] -> 0.20720124 | O12: =Table7[[#This Row],[Operating_Inflows]]-Table7[[#This Row],[Operating_Outflows]] -> 187.6 | P12: =0.4*Table7[[#This Row],[Financing_Outflows]] -> 59.44
A13: 45992 | B13: 993 | C13: 824 | D13: 326.9 | E13: 56.1 | F13: 138.8 | G13: =Table7[[#This Row],[Operating_Inflows]]-Table7[[#This Row],[Operating_Outflows]]-Table7[[#This Row],[Investing_Outflows]]+Table7[[#This Row],[Financing_Inflows]]-Table7[[#This Row],[Financing_Outflows]] -> -240.6 | H13: 983.8 | I13: 536.2 | J13: =Table7[[#This Row],[Operating_Inflows]]-Table7[[#This Row],[Operating_Outflows]]-Table7[[#This Row],[Investing_Outflows]] -> -157.9 | K13: =Table7[[#This Row],[FCF]]/Table7[[#This Row],[EBITDA/EBIT_PROXY]] -> -0.93431953 | L13: =Table7[[#This Row],[forecast_closing]]/(Table7[[#This Row],[Operating_Outflows]]/12) -> 7.8087379 | M13: =Table7[[#This Row],[EBITDA/EBIT_PROXY]]/Table7[[#This Row],[INTEREST PROXY]] -> 3.0439481 | N13: =Table7[[#This Row],[EBITDA/EBIT_PROXY]]/Table7[[#This Row],[Operating_Inflows]] -> 0.17019134 | O13: =Table7[[#This Row],[Operating_Inflows]]-Table7[[#This Row],[Operating_Outflows]] -> 169 | P13: =0.4*Table7[[#This Row],[Financing_Outflows]] -> 55.52
A14: 46023 | B14: =B13*(1+Controls!$C$6/100) -> 1022.79 | C14: =C13*(1+Controls!$C$7/100) -> 844.6 | D14: =Controls!$C$9/12 -> 133.33333 | E14: 75.7 | F14: 126.4 | G14: =Table7[[#This Row],[Operating_Inflows]]-Table7[[#This Row],[Operating_Outflows]]-Table7[[#This Row],[Investing_Outflows]]+Table7[[#This Row],[Financing_Inflows]]-Table7[[#This Row],[Financing_Outflows]] -> -5.8433333 | H14: =I13 -> 536.2 | I14: =Table7[[#This Row],[forecast_opening]]+Table7[[#This Row],[forecast_net]] -> 530.35667 | J14: =Table7[[#This Row],[Operating_Inflows]]-Table7[[#This Row],[Operating_Outflows]]-Table7[[#This Row],[Investing_Outflows]] -> 44.856667 | K14: =Table7[[#This Row],[FCF]]/Table7[[#This Row],[EBITDA/EBIT_PROXY]] -> 0.25173504 | L14: =Table7[[#This Row],[forecast_closing]]/(Table7[[#This Row],[Operating_Outflows]]/12) -> 7.5352593 | M14: =Table7[[#This Row],[EBITDA/EBIT_PROXY]]/Table7[[#This Row],[INTEREST PROXY]] -> 3.5243275 | N14: =Table7[[#This Row],[EBITDA/EBIT_PROXY]]/Table7[[#This Row],[Operating_Inflows]] -> 0.17421954 | O14: =Table7[[#This Row],[Operating_Inflows]]-Table7[[#This Row],[Operating_Outflows]] -> 178.19 | P14: =0.4*Table7[[#This Row],[Financing_Outflows]] -> 50.56
A15: 46054 | B15: =B14*(1+Controls!$C$6/100) -> 1053.4737 | C15: =C14*(1+Controls!$C$7/100) -> 865.715 | D15: =Controls!$C$9/12 -> 133.33333 | E15: 84.9 | F15: 118.1 | G15: =Table7[[#This Row],[Operating_Inflows]]-Table7[[#This Row],[Operating_Outflows]]-Table7[[#This Row],[Investing_Outflows]]+Table7[[#This Row],[Financing_Inflows]]-Table7[[#This Row],[Financing_Outflows]] -> 21.225367 | H15: =I14 -> 530.35667 | I15: =Table7[[#This Row],[forecast_opening]]+Table7[[#This Row],[forecast_net]] -> 551.58203 | J15: =Table7[[#This Row],[Operating_Inflows]]-Table7[[#This Row],[Operating_Outflows]]-Table7[[#This Row],[Investing_Outflows]] -> 54.425367 | K15: =Table7[[#This Row],[FCF]]/Table7[[#This Row],[EBITDA/EBIT_PROXY]] -> 0.28986868 | L15: =Table7[[#This Row],[forecast_closing]]/(Table7[[#This Row],[Operating_Outflows]]/12) -> 7.6456852 | M15: =Table7[[#This Row],[EBITDA/EBIT_PROXY]]/Table7[[#This Row],[INTEREST PROXY]] -> 3.9745703 | N15: =Table7[[#This Row],[EBITDA/EBIT_PROXY]]/Table7[[#This Row],[Operating_Inflows]] -> 0.17822818 | O15: =Table7[[#This Row],[Operating_Inflows]]-Table7[[#This Row],[Operating_Outflows]] -> 187.7587 | P15: =0.4*Table7[[#This Row],[Financing_Outflows]] -> 47.24
A16: 46082 | B16: =B15*(1+Controls!$C$6/100) -> 1085.0779 | C16: =C15*(1+Controls!$C$7/100) -> 887.35787 | D16: =Controls!$C$9/12 -> 133.33333 | E16: 127.5 | F16: 72 | G16: =Table7[[#This Row],[Operating_Inflows]]-Table7[[#This Row],[Operating_Outflows]]-Table7[[#This Row],[Investing_Outflows]]+Table7[[#This Row],[Financing_Inflows]]-Table7[[#This Row],[Financing_Outflows]] -> 119.8867 | H16: =I15 -> 551.58203 | I16: =Table7[[#This Row],[forecast_opening]]+Table7[[#This Row],[forecast_net]] -> 671.46874 | J16: =Table7[[#This Row],[Operating_Inflows]]-Table7[[#This Row],[Operating_Outflows]]-Table7[[#This Row],[Investing_Outflows]] -> 64.386703 | K16: =Table7[[#This Row],[FCF]]/Table7[[#This Row],[EBITDA/EBIT_PROXY]] -> 0.32564582 | L16: =Table7[[#This Row],[forecast_closing]]/(Table7[[#This Row],[Operating_Outflows]]/12) -> 9.080468 | M16: =Table7[[#This Row],[EBITDA/EBIT_PROXY]]/Table7[[#This Row],[INTEREST PROXY]] -> 6.865279 | N16: =Table7[[#This Row],[EBITDA/EBIT_PROXY]]/Table7[[#This Row],[Operating_Inflows]] -> 0.18221736 | O16: =Table7[[#This Row],[Operating_Inflows]]-Table7[[#This Row],[Operating_Outflows]] -> 197.72004 | P16: =0.4*Table7[[#This Row],[Financing_Outflows]] -> 28.8
A17: 46113 | B17: =B16*(1+Controls!$C$6/100) -> 1117.6302 | C17: =C16*(1+Controls!$C$7/100) -> 909.54182 | D17: =Controls!$C$9/12 -> 133.33333 | E17: 109.9 | F17: 119.3 | G17: =Table7[[#This Row],[Operating_Inflows]]-Table7[[#This Row],[Operating_Outflows]]-Table7[[#This Row],[Investing_Outflows]]+Table7[[#This Row],[Financing_Inflows]]-Table7[[#This Row],[Financing_Outflows]] -> 65.355093 | H17: =I16 -> 671.46874 | I17: =Table7[[#This Row],[forecast_opening]]+Table7[[#This Row],[forecast_net]] -> 736.82383 | J17: =Table7[[#This Row],[Operating_Inflows]]-Table7[[#This Row],[Operating_Outflows]]-Table7[[#This Row],[Investing_Outflows]] -> 74.755093 | K17: =Table7[[#This Row],[FCF]]/Table7[[#This Row],[EBITDA/EBIT_PROXY]] -> 0.35924676 | L17: =Table7[[#This Row],[forecast_closing]]/(Table7[[#This Row],[Operating_Outflows]]/12) -> 9.7212528 | M17: =Table7[[#This Row],[EBITDA/EBIT_PROXY]]/Table7[[#This Row],[INTEREST PROXY]] -> 4.3606125 | N17: =Table7[[#This Row],[EBITDA/EBIT_PROXY]]/Table7[[#This Row],[Operating_Inflows]] -> 0.18618718 | O17: =Table7[[#This Row],[Operating_Inflows]]-Table7[[#This Row],[Operating_Outflows]] -> 208.08843 | P17: =0.4*Table7[[#This Row],[Financing_Outflows]] -> 47.72
A18: 46143 | B18: =B17*(1+Controls!$C$6/100) -> 1151.1592 | C18: =C17*(1+Controls!$C$7/100) -> 932.28037 | D18: =Controls!$C$9/12 -> 133.33333 | E18: 84.1 | F18: 121.5 | G18: =Table7[[#This Row],[Operating_Inflows]]-Table7[[#This Row],[Operating_Outflows]]-Table7[[#This Row],[Investing_Outflows]]+Table7[[#This Row],[Financing_Inflows]]-Table7[[#This Row],[Financing_Outflows]] -> 48.145455 | H18: =I17 -> 736.82383 | I18: =Table7[[#This Row],[forecast_opening]]+Table7[[#This Row],[forecast_net]] -> 784.96928 | J18: =Table7[[#This Row],[Operating_Inflows]]-Table7[[#This Row],[Operating_Outflows]]-Table7[[#This Row],[Investing_Outflows]] -> 85.545455 | K18: =Table7[[#This Row],[FCF]]/Table7[[#This Row],[EBITDA/EBIT_PROXY]] -> 0.39083483 | L18: =Table7[[#This Row],[forecast_closing]]/(Table7[[#This Row],[Operating_Outflows]]/12) -> 10.103861 | M18: =Table7[[#This Row],[EBITDA/EBIT_PROXY]]/Table7[[#This Row],[INTEREST PROXY]] -> 4.5036788 | N18: =Table7[[#This Row],[EBITDA/EBIT_PROXY]]/Table7[[#This Row],[Operating_Inflows]] -> 0.19013773 | O18: =Table7[[#This Row],[Operating_Inflows]]-Table7[[#This Row],[Operating_Outflows]] -> 218.87879 | P18: =0.4*Table7[[#This Row],[Financing_Outflows]] -> 48.6
A19: 46174 | B19: =B18*(1+Controls!$C$6/100) -> 1185.6939 | C19: =C18*(1+Controls!$C$7/100) -> 955.58738 | D19: =Controls!$C$9/12 -> 133.33333 | E19: 115.4 | F19: 181.6 | G19: =Table7[[#This Row],[Operating_Inflows]]-Table7[[#This Row],[Operating_Outflows]]-Table7[[#This Row],[Investing_Outflows]]+Table7[[#This Row],[Financing_Inflows]]-Table7[[#This Row],[Financing_Outflows]] -> 30.573221 | H19: =I18 -> 784.96928 | I19: =Table7[[#This Row],[forecast_opening]]+Table7[[#This Row],[forecast_net]] -> 815.5425 | J19: =Table7[[#This Row],[Operating_Inflows]]-Table7[[#This Row],[Operating_Outflows]]-Table7[[#This Row],[Investing_Outflows]] -> 96.773221 | K19: =Table7[[#This Row],[FCF]]/Table7[[#This Row],[EBITDA/EBIT_PROXY]] -> 0.4205583 | L19: =Table7[[#This Row],[forecast_closing]]/(Table7[[#This Row],[Operating_Outflows]]/12) -> 10.241356 | M19: =Table7[[#This Row],[EBITDA/EBIT_PROXY]]/Table7[[#This Row],[INTEREST PROXY]] -> 3.1677664 | N19: =Table7[[#This Row],[EBITDA/EBIT_PROXY]]/Table7[[#This Row],[Operating_Inflows]] -> 0.1940691 | O19: =Table7[[#This Row],[Operating_Inflows]]-Table7[[#This Row],[Operating_Outflows]] -> 230.10655 | P19: =0.4*Table7[[#This Row],[Financing_Outflows]] -> 72.64
A20: 46204 | B20: =B19*(1+Controls!$C$6/100) -> 1221.2647 | C20: =C19*(1+Controls!$C$7/100) -> 979.47706 | D20: =Controls!$C$9/12 -> 133.33333 | E20: 102.9 | F20: 115.2 | G20: =Table7[[#This Row],[Operating_Inflows]]-Table7[[#This Row],[Operating_Outflows]]-Table7[[#This Row],[Investing_Outflows]]+Table7[[#This Row],[Financing_Inflows]]-Table7[[#This Row],[Financing_Outflows]] -> 96.154354 | H20: =I19 -> 815.5425 | I20: =Table7[[#This Row],[forecast_opening]]+Table7[[#This Row],[forecast_net]] -> 911.69686 | J20: =Table7[[#This Row],[Operating_Inflows]]-Table7[[#This Row],[Operating_Outflows]]-Table7[[#This Row],[Investing_Outflows]] -> 108.45435 | K20: =Table7[[#This Row],[FCF]]/Table7[[#This Row],[EBITDA/EBIT_PROXY]] -> 0.44855201 | L20: =Table7[[#This Row],[forecast_closing]]/(Table7[[#This Row],[Operating_Outflows]]/12) -> 11.169595 | M20: =Table7[[#This Row],[EBITDA/EBIT_PROXY]]/Table7[[#This Row],[INTEREST PROXY]] -> 5.2471286 | N20: =Table7[[#This Row],[EBITDA/EBIT_PROXY]]/Table7[[#This Row],[Operating_Inflows]] -> 0.19798139 | O20: =Table7[[#This Row],[Operating_Inflows]]-Table7[[#This Row],[Operating_Outflows]] -> 241.78769 | P20: =0.4*Table7[[#This Row],[Financing_Outflows]] -> 46.08
A21: 46235 | B21: =B20*(1+Controls!$C$6/100) -> 1257.9027 | C21: =C20*(1+Controls!$C$7/100) -> 1003.964 | D21: =Controls!$C$9/12 -> 133.33333 | E21: 129.1 | F21: 127.5 | G21: =Table7[[#This Row],[Operating_Inflows]]-Table7[[#This Row],[Operating_Outflows]]-Table7[[#This Row],[Investing_Outflows]]+Table7[[#This Row],[Financing_Inflows]]-Table7[[#This Row],[Financing_Outflows]] -> 122.20537 | H21: =I20 -> 911.69686 | I21: =Table7[[#This Row],[forecast_opening]]+Table7[[#This Row],[forecast_net]] -> 1033.9022 | J21: =Table7[[#This Row],[Operating_Inflows]]-Table7[[#This Row],[Operating_Outflows]]-Table7[[#This Row],[Investing_Outflows]] -> 120.60537 | K21: =Table7[[#This Row],[FCF]]/Table7[[#This Row],[EBITDA/EBIT_PROXY]] -> 0.47493891 | L21: =Table7[[#This Row],[forecast_closing]]/(Table7[[#This Row],[Operating_Outflows]]/12) -> 12.35784 | M21: =Table7[[#This Row],[EBITDA/EBIT_PROXY]]/Table7[[#This Row],[INTEREST PROXY]] -> 4.9791903 | N21: =Table7[[#This Row],[EBITDA/EBIT_PROXY]]/Table7[[#This Row],[Operating_Inflows]] -> 0.20187468 | O21: =Table7[[#This Row],[Operating_Inflows]]-Table7[[#This Row],[Operating_Outflows]] -> 253.9387 | P21: =0.4*Table7[[#This Row],[Financing_Outflows]] -> 51
A22: 46266 | B22: =B21*(1+Controls!$C$6/100) -> 1295.6398 | C22: =C21*(1+Controls!$C$7/100) -> 1029.0631 | D22: =Controls!$C$9/12 -> 133.33333 | E22: 78.9 | F22: 119.1 | G22: =Table7[[#This Row],[Operating_Inflows]]-Table7[[#This Row],[Operating_Outflows]]-Table7[[#This Row],[Investing_Outflows]]+Table7[[#This Row],[Financing_Inflows]]-Table7[[#This Row],[Financing_Outflows]] -> 93.043351 | H22: =I21 -> 1033.9022 | I22: =Table7[[#This Row],[forecast_opening]]+Table7[[#This Row],[forecast_net]] -> 1126.9456 | J22: =Table7[[#This Row],[Operating_Inflows]]-Table7[[#This Row],[Operating_Outflows]]-Table7[[#This Row],[Investing_Outflows]] -> 133.24335 | K22: =Table7[[#This Row],[FCF]]/Table7[[#This Row],[EBITDA/EBIT_PROXY]] -> 0.49983123 | L22: =Table7[[#This Row],[forecast_closing]]/(Table7[[#This Row],[Operating_Outflows]]/12) -> 13.141417 | M22: =Table7[[#This Row],[EBITDA/EBIT_PROXY]]/Table7[[#This Row],[INTEREST PROXY]] -> 5.5956483 | N22: =Table7[[#This Row],[EBITDA/EBIT_PROXY]]/Table7[[#This Row],[Operating_Inflows]] -> 0.20574907 | O22: =Table7[[#This Row],[Operating_Inflows]]-Table7[[#This Row],[Operating_Outflows]] -> 266.57668 | P22: =0.4*Table7[[#This Row],[Financing_Outflows]] -> 47.64
A23: 46296 | B23: =B22*(1+Controls!$C$6/100) -> 1334.509 | C23: =C22*(1+Controls!$C$7/100) -> 1054.7897 | D23: =Controls!$C$9/12 -> 133.33333 | E23: 90.2 | F23: 90.8 | G23: =Table7[[#This Row],[Operating_Inflows]]-Table7[[#This Row],[Operating_Outflows]]-Table7[[#This Row],[Investing_Outflows]]+Table7[[#This Row],[Financing_Inflows]]-Table7[[#This Row],[Financing_Outflows]] -> 145.78597 | H23: =I22 -> 1126.9456 | I23: =Table7[[#This Row],[forecast_opening]]+Table7[[#This Row],[forecast_net]] -> 1272.7315 | J23: =Table7[[#This Row],[Operating_Inflows]]-Table7[[#This Row],[Operating_Outflows]]-Table7[[#This Row],[Investing_Outflows]] -> 146.38597 | K23: =Table7[[#This Row],[FCF]]/Table7[[#This Row],[EBITDA/EBIT_PROXY]] -> 0.52333166 | L23: =Table7[[#This Row],[forecast_closing]]/(Table7[[#This Row],[Operating_Outflows]]/12) -> 14.479454 | M23: =Table7[[#This Row],[EBITDA/EBIT_PROXY]]/Table7[[#This Row],[INTEREST PROXY]] -> 7.7015226 | N23: =Table7[[#This Row],[EBITDA/EBIT_PROXY]]/Table7[[#This Row],[Operating_Inflows]] -> 0.20960466 | O23: =Table7[[#This Row],[Operating_Inflows]]-Table7[[#This Row],[Operating_Outflows]] -> 279.7193 | P23: =0.4*Table7[[#This Row],[Financing_Outflows]] -> 36.32
A24: 46327 | B24: =B23*(1+Controls!$C$6/100) -> 1374.5442 | C24: =C23*(1+Controls!$C$7/100) -> 1081.1594 | D24: =Controls!$C$9/12 -> 133.33333 | E24: 88.2 | F24: 148.6 | G24: =Table7[[#This Row],[Operating_Inflows]]-Table7[[#This Row],[Operating_Outflows]]-Table7[[#This Row],[Investing_Outflows]]+Table7[[#This Row],[Financing_Inflows]]-Table7[[#This Row],[Financing_Outflows]] -> 99.651494 | H24: =I23 -> 1272.7315 | I24: =Table7[[#This Row],[forecast_opening]]+Table7[[#This Row],[forecast_net]] -> 1372.383 | J24: =Table7[[#This Row],[Operating_Inflows]]-Table7[[#This Row],[Operating_Outflows]]-Table7[[#This Row],[Investing_Outflows]] -> 160.05149 | K24: =Table7[[#This Row],[FCF]]/Table7[[#This Row],[EBITDA/EBIT_PROXY]] -> 0.54553433 | L24: =Table7[[#This Row],[forecast_closing]]/(Table7[[#This Row],[Operating_Outflows]]/12) -> 15.232348 | M24: =Table7[[#This Row],[EBITDA/EBIT_PROXY]]/Table7[[#This Row],[INTEREST PROXY]] -> 4.9358147 | N24: =Table7[[#This Row],[EBITDA/EBIT_PROXY]]/Table7[[#This Row],[Operating_Inflows]] -> 0.21344153 | O24: =Table7[[#This Row],[Operating_Inflows]]-Table7[[#This Row],[Operating_Outflows]] -> 293.38483 | P24: =0.4*Table7[[#This Row],[Financing_Outflows]] -> 59.44
A25: 46357 | B25: =B24*(1+Controls!$C$6/100) -> 1415.7806 | C25: =C24*(1+Controls!$C$7/100) -> 1108.1884 | D25: =Controls!$C$9/12 -> 133.33333 | E25: 56.1 | F25: 138.8 | G25: =Table7[[#This Row],[Operating_Inflows]]-Table7[[#This Row],[Operating_Outflows]]-Table7[[#This Row],[Investing_Outflows]]+Table7[[#This Row],[Financing_Inflows]]-Table7[[#This Row],[Financing_Outflows]] -> 91.558836 | H25: =I24 -> 1372.383 | I25: =Table7[[#This Row],[forecast_opening]]+Table7[[#This Row],[forecast_net]] -> 1463.9419 | J25: =Table7[[#This Row],[Operating_Inflows]]-Table7[[#This Row],[Operating_Outflows]]-Table7[[#This Row],[Investing_Outflows]] -> 174.25884 | K25: =Table7[[#This Row],[FCF]]/Table7[[#This Row],[EBITDA/EBIT_PROXY]] -> 0.56652559 | L25: =Table7[[#This Row],[forecast_closing]]/(Table7[[#This Row],[Operating_Outflows]]/12) -> 15.852271 | M25: =Table7[[#This Row],[EBITDA/EBIT_PROXY]]/Table7[[#This Row],[INTEREST PROXY]] -> 5.5402048 | N25: =Table7[[#This Row],[EBITDA/EBIT_PROXY]]/Table7[[#This Row],[Operating_Inflows]] -> 0.21725978 | O25: =Table7[[#This Row],[Operating_Inflows]]-Table7[[#This Row],[Operating_Outflows]] -> 307.59217 | P25: =0.4*Table7[[#This Row],[Financing_Outflows]] -> 55.52
